Metadata-Version: 1.0
Name: fakelogs
Version: 1.0.0
Summary: fakelogs - library for generating fake logs
Home-page: https://github.com/teriyakichild/fakelogs
Author: Tony Rogers
Author-email: tony.rogers@logdna.com
License: ASLv2
Platform: UNKNOWN
